aladeen_metadata_extractor/__init__.py
aladeen_metadata_extractor/clients/anthropic.py
aladeen_metadata_extractor/clients/openai.py
aladeen_metadata_extractor/main.py
aladeen_metadata_extractor/types/client.py
aladeen_metadata_extractor/types/errors.py
aladeen_metadata_extractor/types/misc.py
aladeen_metadata_extractor-0.3.0.dist-info/METADATA
aladeen_metadata_extractor-0.3.0.dist-info/WHEEL
aladeen_metadata_extractor-0.3.0.dist-info/RECORD
